{
  "prepare_queue": {
    "installed": [],
    "uninstalled": []
  },
  "config_munge": {
    "files": {}
  },
  "installed_plugins": {
    "cordova-plugin-whitelist": {
      "PACKAGE_NAME": "com.example.stampRally"
    },
    "cordova-plugin-camera": {
      "PACKAGE_NAME": "com.example.stampRally"
    },
    "cordova-plugin-dialogs": {
      "PACKAGE_NAME": "com.example.stampRally"
    },
    "cordova-plugin-device": {
      "PACKAGE_NAME": "com.example.stampRally"
    },
    "phonegap-plugin-barcodescanner": {
      "PACKAGE_NAME": "com.example.stampRally"
    },
    "cordova-plugin-geolocation": {
      "PACKAGE_NAME": "com.example.stampRally"
    },
    "cordova-plugin-file": {
      "PACKAGE_NAME": "com.example.stampRally"
    }
  },
  "dependent_plugins": {}
}